{
  "topic_id": "work_transition",
  "topic_label": "Arbeit im Wandel",
  "article_count": 458,
  "candidate_count": 800,
  "outlets": {
    "tagesschau": {
      "source_id": "tagesschau",
      "source": "Tagesschau (ARD)",
      "bias": "neutral",
      "article_count": 72,
      "sample_titles": [
        "Saarbahn-Tarifstreit: Arbeitgeber legt erstes Angebot vor",
        "Bundesweiter Streik im Einzelhandel trifft auch das Saarland",
        "Beschäftigung in der Industrie auf Zehnjahrestief",
        "Bas' Arbeitszeit-Pläne sorgen für scharfe Kritik"
      ],
      "urls": [
        "https://www.sr.de/sr/home/nachrichten/politik_wirtschaft/saarbahn_tarifstreit_arbeitgeberangebot_100.html",
        "https://www.sr.de/sr/home/nachrichten/politik_wirtschaft/bundesweiter_streik_im_einzelhandel_saarland_100.html",
        "https://www1.wdr.de/wirtschaft/bertelsmann-stiftung-industrie-stellenabbau-100.html",
        "https://www.tagesschau.de/inland/innenpolitik/entwurf-arbeitszeitgesetz-100.html"
      ],
      "dominant_emotion": "approval",
      "top_emotions": [
        {
          "emotion": "approval",
          "count": 4
        },
        {
          "emotion": "desire",
          "count": 4
        },
        {
          "emotion": "annoyance",
          "count": 3
        }
      ]
    },
    "welt": {
      "source_id": "welt",
      "source": "Die Welt",
      "bias": "right-conservative",
      "article_count": 52,
      "sample_titles": [
        "Söder fordert Kürzung des Bürgergeldes „bis auf das absolut verfassungsrechtliche Minimum“",
        "Union wirft Bärbel Bas Vertragsbruch bei Arbeitszeitreform vor",
        "Arbeitszeit-Reform sorgt für Streit – Arbeitgeber kritisieren Regierungspläne scharf",
        "„Keine Grundlage für weitere Arbeit“ – Linnemann wirft Bas Koalitionsbruch vor"
      ],
      "urls": [
        "https://www.welt.de/politik/deutschland/article6a374ed27e682fc37fc02074/markus-soeder-fordert-kuerzung-des-buergergeldes-bis-auf-das-absolute-minimum.html",
        "https://www.welt.de/videos/video6a34ede25e7a993acdae331e/reformstau-union-wirft-baerbel-bas-vertragsbruch-bei-arbeitszeitreform-vor.html",
        "https://www.welt.de/videos/video6a33fc8946cd409e901a5fa1/acht-stunden-tag-arbeitszeit-reform-sorgt-fuer-streit-arbeitgeber-kritisieren-regierungsplaene-scharf.html",
        "https://www.welt.de/politik/deutschland/article6a33c035a7834e0047eee0c7/acht-stunden-tag-keine-grundlage-fuer-weitere-arbeit-cdu-politiker-werfen-bas-koalitionsbruch-vor.html"
      ],
      "dominant_emotion": "optimism",
      "top_emotions": [
        {
          "emotion": "optimism",
          "count": 3
        },
        {
          "emotion": "desire",
          "count": 2
        },
        {
          "emotion": "annoyance",
          "count": 1
        }
      ]
    },
    "ntv": {
      "source_id": "ntv",
      "source": "n-tv",
      "bias": "right-conservative",
      "article_count": 50,
      "sample_titles": [
        "Weniger Leistungen für Ukrainer: Söder will Bürgergeld kürzen und Bezahlkarte ausweiten",
        "Gespräche mit Betriebsrat: BMW stimmt Belegschaft auf Sparprogramm ein",
        "Heiß, heißer, ab nach Hause?: Diese Rechte haben Arbeitnehmer bei Hitze",
        "Reform des Acht-Stunden-Tags: Arbeitgeber und CDU hauen Bärbel Bas Gesetzentwurf um die Ohren"
      ],
      "urls": [
        "https://www.n-tv.de/politik/Soeder-will-Buergergeld-kuerzen-und-Bezahlkarte-ausweiten-id30992291.html",
        "https://www.n-tv.de/wirtschaft/BMW-stimmt-Belegschaft-auf-Sparprogramm-ein-id30988330.html",
        "https://www.n-tv.de/ratgeber/Diese-Rechte-haben-Arbeitnehmer-bei-Hitze-id30865731.html",
        "https://www.n-tv.de/politik/Arbeitgeber-und-CDU-hauen-Baerbel-Bas-Gesetzentwurf-um-die-Ohren-id30983403.html"
      ],
      "dominant_emotion": "curiosity",
      "top_emotions": [
        {
          "emotion": "curiosity",
          "count": 3
        },
        {
          "emotion": "optimism",
          "count": 3
        },
        {
          "emotion": "annoyance",
          "count": 2
        }
      ]
    },
    "faz": {
      "source_id": "faz",
      "source": "FAZ",
      "bias": "conservative-liberal",
      "article_count": 48,
      "sample_titles": [
        "Wochen- statt Tageslimit: Lässt Bas die Reform der Arbeitszeitregeln platzen?",
        "Studie: Industrie-Beschäftigung fällt auf Zehnjahrestief",
        "Konzernumbau: Der nächste Sparten-Börsengang von Thyssenkrupp kommt",
        "KI als Jobkiller?: Von wegen Jobapokalypse!"
      ],
      "urls": [
        "https://www.faz.net/aktuell/wirtschaft/laesst-bas-die-reform-der-arbeitszeitregeln-platzen-200943011.html",
        "https://www.faz.net/aktuell/wirtschaft/unternehmen/industrie-beschaeftigung-in-deutschland-auf-zehnjahrestief-accg-200941823.html",
        "https://www.faz.net/aktuell/wirtschaft/unternehmen/der-naechste-sparten-boersengang-von-thyssenkrupp-kommt-200936786.html",
        "https://www.faz.net/aktuell/wirtschaft/ki-als-jobkiller-was-der-us-arbeitsmarkt-zeigt-200910894.html"
      ],
      "dominant_emotion": "optimism",
      "top_emotions": [
        {
          "emotion": "optimism",
          "count": 7
        },
        {
          "emotion": "confusion",
          "count": 3
        },
        {
          "emotion": "realization",
          "count": 3
        }
      ]
    },
    "stern": {
      "source_id": "stern",
      "source": "Stern",
      "bias": "left-liberal",
      "article_count": 42,
      "sample_titles": [
        "Soziales: Söder fordert Bürgergeld-Kürzung",
        "Debatte zu Wirtschaftspolitik: Reformentwurf zum Achtstundentag stößt in MV auf Kritik",
        "Medienberichte: Bas will Höchstwochenarbeitszeit an Tarifverträge knüpfen",
        "Bier-Preise bei der WM: Ein Bier für den Mindestlohn: „Absurde Preise“ bei der WM"
      ],
      "urls": [
        "https://www.stern.de/politik/deutschland/soziales--soeder-fordert-buergergeld-kuerzung-37576792.html",
        "https://www.stern.de/gesellschaft/regional/mecklenburg-vorpommern/debatte-zu-wirtschaftspolitik--reformentwurf-zum-achtstundentag-stoesst-in-mv-auf-kritik-37568056.html",
        "https://www.stern.de/news/medienberichte--bas-will-hoechstwochenarbeitszeit-an-tarifvertraege-knuepfen-37564842.html",
        "https://www.stern.de/sport/bier-preise-bei-der-wm--ein-bier-fuer-den-mindestlohn---absurde-preise--bei-der-wm-37555538.html"
      ],
      "dominant_emotion": "curiosity",
      "top_emotions": [
        {
          "emotion": "curiosity",
          "count": 1
        },
        {
          "emotion": "excitement",
          "count": 1
        },
        {
          "emotion": "joy",
          "count": 1
        }
      ]
    },
    "spiegel": {
      "source_id": "spiegel",
      "source": "Spiegel Online",
      "bias": "left-liberal",
      "article_count": 40,
      "sample_titles": [
        "Arbeitszeitgesetz: Entwurf aus dem Ministerium löst Streit mit Union aus",
        "Einzelhandel: Ver.di will mehr als die Hälfte der Ikea-Filialen bestreiken",
        "Wöchentliche Arbeitszeit: Tarifgebundene Firmen sollen Achtstundentag lockern können",
        "Arbeitsmarkt: Wo es offene Stellen gibt und Fachkräfte fehlen – eine interaktive Karte"
      ],
      "urls": [
        "https://www.spiegel.de/wirtschaft/arbeitszeitgesetz-entwurf-aus-dem-ministerium-loest-streit-mit-union-aus-a-a8a95867-889e-41d3-a31e-5b2ce96d1cf4#ref=rss",
        "https://www.spiegel.de/wirtschaft/unternehmen/einzelhandel-ver-di-will-mehr-als-die-haelfte-der-ikea-filialen-bestreiken-a-809f3dd5-a109-40b0-921e-71831441403b#ref=rss",
        "https://www.spiegel.de/wirtschaft/unternehmen/woechentliche-arbeitszeit-tarifgebundene-firmen-sollen-achtstundentag-lockern-koennen-a-bd83649d-86ba-4fd2-b8bd-5637dc762d03#ref=rss",
        "https://www.spiegel.de/karriere/arbeitsmarkt-wo-es-offene-stellen-gibt-und-fachkraefte-fehlen-eine-interaktive-karte-a-e851703d-330c-4d91-a1c4-18e1563b3067#ref=rss"
      ],
      "dominant_emotion": "disapproval",
      "top_emotions": [
        {
          "emotion": "disapproval",
          "count": 4
        },
        {
          "emotion": "optimism",
          "count": 3
        },
        {
          "emotion": "confusion",
          "count": 2
        }
      ]
    },
    "handelsblatt": {
      "source_id": "handelsblatt",
      "source": "Handelsblatt",
      "bias": "economic-liberal",
      "article_count": 38,
      "sample_titles": [
        "Autoindustrie: BMW bereitet Gespräche mit Betriebsrat über Kostensenkungen vor",
        "Gastkommentar: Mehr Gehalt statt Kündigungsschutz: Ein Wahlrecht könnte den deutschen Arbeitsmarkt revolutionieren",
        "Arbeitszeit: Arbeitsministerin Bas will Acht-Stunden-Tag nicht generell lockern – Union kritisiert Entwurf",
        "Industrie: Kompromiss bei Thyssenkrupp: Aufsichtsrat gibt grünes Licht für Abspaltung von Materials Services"
      ],
      "urls": [
        "https://www.handelsblatt.com/unternehmen/dienstleister/autoindustrie-bmw-bereitet-gespraeche-mit-betriebsrat-ueber-kostensenkungen-vor/100234413.html",
        "https://www.handelsblatt.com/meinung/gastbeitraege/gastkommentar-mehr-gehalt-statt-kuendigungsschutz-so-kaeme-deutschland-nach-vorne/100233654.html",
        "https://www.handelsblatt.com/politik/deutschland/arbeitszeit-arbeitsministerin-bas-will-achtstundentag-nicht-generell-lockern/100234028.html",
        "https://www.handelsblatt.com/unternehmen/industrie/thyssenkrupp-thyssenkrupp-aufsichtsrat-billigt-abspaltung-von-materials-services/100231582.html"
      ],
      "dominant_emotion": "optimism",
      "top_emotions": [
        {
          "emotion": "optimism",
          "count": 4
        },
        {
          "emotion": "annoyance",
          "count": 1
        },
        {
          "emotion": "confusion",
          "count": 1
        }
      ]
    },
    "bild": {
      "source_id": "bild",
      "source": "BILD",
      "bias": "populist-mixed",
      "article_count": 28,
      "sample_titles": [
        "Rente, Steuern und Sozialstaat - Söder will ans Bürgergeld!",
        "Firmenchefs berichten - So arbeitsunwillig sind viele Stütze-Empfänger",
        "Koalitionskrach um Arbeitszeit - Bas macht mit 8-Stunden-Tag die Union wütend",
        "Nach Dobrindts Vorstoß - Sinkt jetzt das Bürgergeld?"
      ],
      "urls": [
        "https://www.bild.de/politik/inland/markus-soeder-wehrt-sich-csu-rumort-rentenstreit-und-buergergeld-debatte-6a3561a87e682fc37fc00d12",
        "https://www.bild.de/politik/inland/firmenchefs-packen-aus-so-arbeitsunwillig-sind-viele-stuetze-empfaenger-6a311bb1a8614079727d7b8d",
        "https://www.bild.de/politik/inland/koalitionskrach-um-arbeitszeit-so-will-bas-den-8-stunden-tag-retten-6a33e53f7e682fc37fbff614",
        "https://www.bild.de/politik/inland/sinkt-jetzt-das-buergergeld-alexander-dobrindt-stoesst-debatte-an-6a32a3cca7834e0047eed0ce"
      ],
      "dominant_emotion": "realization",
      "top_emotions": [
        {
          "emotion": "realization",
          "count": 1
        },
        {
          "emotion": "anger",
          "count": 1
        },
        {
          "emotion": "fear",
          "count": 1
        }
      ]
    },
    "zdf": {
      "source_id": "zdf",
      "source": "ZDF heute",
      "bias": "neutral",
      "article_count": 21,
      "sample_titles": [
        "Studie: Abwärtstrend bei der Industriebeschäftigung",
        "Spahn drängt auf Umsetzung der Arbeitszeitreform",
        "Nach Spitzentreffen: Weitere Gespräche geplant",
        "DGB-Vorsitzende Fahimi will Betriebsrenten-Pflicht für alle"
      ],
      "urls": [
        "https://www.zdfheute.de/wirtschaft/industrie-beschaeftigte-deutschland-gesunken-100.html",
        "https://www.zdfheute.de/politik/deutschland/jens-sphan-flexiblere-arbeitszeiten-100.html",
        "https://www.zdfheute.de/politik/deutschland/koalition-reformgespraeche-spitzentreffen-kanzleramt-gewerkschaften-100.html",
        "https://www.zdfheute.de/politik/deutschland/rente-reform-altersvorsorge-dgb-100.html"
      ],
      "dominant_emotion": "annoyance",
      "top_emotions": [
        {
          "emotion": "annoyance",
          "count": 1
        },
        {
          "emotion": "optimism",
          "count": 1
        },
        {
          "emotion": "disapproval",
          "count": 1
        }
      ]
    },
    "zeit": {
      "source_id": "zeit",
      "source": "Zeit Online",
      "bias": "left-liberal",
      "article_count": 16,
      "sample_titles": [
        "Landesregierung reagiert: Kein Hitzefrei in Ministerien - aber Homeoffice und Wasser",
        "Arbeitszeitgesetz: Bundesarbeitsministerin plant Pflicht zur Arbeitszeiterfassung",
        "Arbeitslosigkeit: Arbeiten trotz Absagen",
        "Udo Dinglreiter: »Jeden Monat werden weitere 10.000 Stellen abgebaut«"
      ],
      "urls": [
        "https://www.zeit.de/news/2026-06/20/kein-hitzefrei-in-ministerien-aber-homeoffice-und-wasser",
        "https://www.zeit.de/politik/deutschland/2026-06/arbeitszeitgesetz-baerbel-bas-reform-arbeitszeiterfassung-tarifvertrag",
        "https://www.zeit.de/campus/2026/02/arbeitslosigkeit-keinen-job-finden-bewerbungen-tipps-strategien",
        "https://www.zeit.de/wirtschaft/2026-06/udo-dinglreiter-gesamtmetall-krise-industrie-deindustrialisierung"
      ],
      "dominant_emotion": "anger",
      "top_emotions": [
        {
          "emotion": "anger",
          "count": 1
        },
        {
          "emotion": "admiration",
          "count": 1
        },
        {
          "emotion": "desire",
          "count": 1
        }
      ]
    },
    "tichys": {
      "source_id": "tichys",
      "source": "Tichys Einblick",
      "bias": "far-right",
      "article_count": 13,
      "sample_titles": [
        "Linnemann: SPD-Entwurf zur Arbeitszeitflexibiliserung keine Grundlage für die weitere Koalitionsarbeit",
        "Zuwanderung von „Fachkräften“ steigt stark: Die Methode Stapelmigration",
        "DGB präsentiert Steuerkonzept: Neiddebatte sticht Arbeitnehmervertretung",
        "ABB-Konzernchef warnt: Europa droht Massen-Arbeitslosigkeit"
      ],
      "urls": [
        "https://www.tichyseinblick.de/meinungen/koalition-streit-linnemann-arbeitszeit-flexibilisierung/",
        "https://www.tichyseinblick.de/daili-es-sentials/zuwanderung-fachkraefte-statistik/",
        "https://www.tichyseinblick.de/wirtschaft/dgb-steuerkonzept-neiddebatte/",
        "https://www.tichyseinblick.de/wirtschaft/abb-europa-droht-massen-arbeitslosigkeit/"
      ],
      "dominant_emotion": "neutral",
      "top_emotions": []
    },
    "taz": {
      "source_id": "taz",
      "source": "taz",
      "bias": "left",
      "article_count": 13,
      "sample_titles": [
        "Neue Grundsicherung tritt in Kraft: „Das wird ein harter Kampf“",
        "Diskussion über Rente in Deutschland: Klingbeil für verpflichtende Betriebsrenten",
        "Altersvorsorge in der Krise: Gewerkschaftsbund fordert Betriebsrente für alle",
        "EU-Vorgaben bei Lohngleichheit: Gleichstellung ist der Bundesregierung zu bürokratisch"
      ],
      "urls": [
        "https://taz.de/Neue-Grundsicherung-tritt-in-Kraft/!6181983/",
        "https://taz.de/Diskussion-ueber-Rente-in-Deutschland/!6185798/",
        "https://taz.de/Altersvorsorge-in-der-Krise/!6185093/",
        "https://taz.de/EU-Vorgaben-bei-Lohngleichheit/!6184970/"
      ],
      "dominant_emotion": "annoyance",
      "top_emotions": [
        {
          "emotion": "annoyance",
          "count": 3
        },
        {
          "emotion": "grief",
          "count": 1
        },
        {
          "emotion": "disapproval",
          "count": 1
        }
      ]
    },
    "sz": {
      "source_id": "sz",
      "source": "Süddeutsche Zeitung",
      "bias": "left-liberal",
      "article_count": 11,
      "sample_titles": [
        "Alterssicherung: Schwarz-grüner Rentenvorstoß im Bundestag",
        "Jobs der Zukunft: Welche Regionen und Branchen gewinnen und verlieren",
        "Abschaffung von Simulatoren: Deutsche Bahn spart an Lokführer-Ausbildung",
        "Bundespolitik: CDU-Arbeitnehmerflügel fordert Einbeziehung der Beamten in die Reformen"
      ],
      "urls": [
        "https://www.sueddeutsche.de/politik/rente-reform-schwarz-gruen-cdu-bundestag-li.3500449",
        "https://www.sueddeutsche.de/projekte/artikel/wirtschaft/deutschland-arbeitsmarkt-regionen-branchen-beschaeftigung-jobs-trump-inflation-china-regierung-industrie-auto-autoindustrie-e149341/",
        "https://www.sueddeutsche.de/wirtschaft/deutsche-bahn-lokfuehrer-ausbildung-simulatoren-spar-druck-li.3496248",
        "https://www.sueddeutsche.de/politik/bundesregierung-liveblog-radke-cdu-arbeitnehmerfluegel-beamte-reform-rente-pflege-gesundheit-li.3495864"
      ],
      "dominant_emotion": "optimism",
      "top_emotions": [
        {
          "emotion": "optimism",
          "count": 2
        },
        {
          "emotion": "admiration",
          "count": 2
        },
        {
          "emotion": "confusion",
          "count": 1
        }
      ]
    },
    "nzz": {
      "source_id": "nzz",
      "source": "Neue Zürcher Zeitung",
      "bias": "conservative-liberal",
      "article_count": 5,
      "sample_titles": [
        "Die EU will mehr Lohngleichheit zwischen Mann und Frau, doch die Mitgliedsländer spielen nicht mit",
        "INTERVIEW - Weniger Lifestyle-Teilzeit, aber trotzdem Frühpensionierungen? «Das ist kein Widerspruch», sagt der oberste Arbeitgeber. «Wir als Gesellschaft müssen länger arbeiten»",
        "40-Stunden-Woche, flexible Arbeitszeiten, Fairtrade-Schoggi: wenn der Zivildienst zum Hochschulpraktikum wird",
        "Unternehmen meiden Deutschland – weil es sie hier teuer zu stehen kommt, Leute zu entlassen"
      ],
      "urls": [
        "https://www.nzz.ch/wirtschaft/die-eu-will-mehr-lohngleichheit-zwischen-mann-und-frau-doch-die-mitgliedslaender-spielen-nicht-mit-ld.10009838",
        "https://www.nzz.ch/schweiz/weniger-lifestyle-teilzeit-aber-trotzdem-fruehpensionierungen-das-ist-kein-widerspruch-sagt-der-oberste-arbeitgeber-wir-als-gesellschaft-muessen-laenger-arbeiten-ld.10008059",
        "https://www.nzz.ch/schweiz/40-stunden-woche-flexible-arbeitszeiten-fairtrade-schoggi-wenn-der-zivildienst-zum-hochschulpraktikum-wird-ld.10005989",
        "https://www.nzz.ch/wirtschaft/unternehmen-meiden-deutschland-weil-es-sie-hier-teuer-zu-stehen-kommt-leute-zu-entlassen-ld.10006308"
      ],
      "dominant_emotion": "desire",
      "top_emotions": [
        {
          "emotion": "desire",
          "count": 1
        },
        {
          "emotion": "anger",
          "count": 1
        }
      ]
    },
    "junge_freiheit": {
      "source_id": "junge_freiheit",
      "source": "Junge Freiheit",
      "bias": "far-right",
      "article_count": 4,
      "sample_titles": [
        "„Vermehrte Streitfälle ums Bürgergeld“ Klagen vor Sozialgerichten steigen rasant an",
        "Höhere Pflegebeiträge Deutscher Gewerkschaftsbund wirft Warken Bestrafung von Kinderlosen vor",
        "Deutschlandticket statt Bargeld? Neuer Streit zwischen Union und SPD ums Bürgergeld",
        "Sozialpolitik Linnemann fordert schärfere Regeln bei Bürgergeld und Grundsicherung"
      ],
      "urls": [
        "https://jungefreiheit.de/politik/deutschland/2026/klagen-vor-sozialgerichten-steigen-rasant-an/",
        "https://jungefreiheit.de/politik/deutschland/2026/deutscher-gewerkschaftsbund-wirft-warken-bestrafung-von-kinderlosen-vor/",
        "https://jungefreiheit.de/politik/deutschland/2026/neuer-streit-zwischen-union-und-spd-ums-buergergeld/",
        "https://jungefreiheit.de/politik/deutschland/2026/linnemann-fordert-schaerfere-regeln-bei-buergergeld-und-grundsicherung/"
      ],
      "dominant_emotion": "disapproval",
      "top_emotions": [
        {
          "emotion": "disapproval",
          "count": 1
        },
        {
          "emotion": "optimism",
          "count": 1
        }
      ]
    },
    "cicero": {
      "source_id": "cicero",
      "source": "Cicero",
      "bias": "conservative-liberal",
      "article_count": 4,
      "sample_titles": [
        "Sind Totalsanktionen im Bürgergeld gerecht? - Von Haltung, Menschenwürde und Selbstverantwortung",
        "Markus Söder bei Caren Miosga - „Auch die Gewerkschaften können nicht nur ,Nein‘ sagen“",
        "Reformdebatte - Während die Gewerkschaften noch mauern, entwickeln andere längst seriöse Reformideen",
        "Bürgergeld im Ausland? - Der „Portugal-Schmarotzer“ – und wie eine Medienerzählung in sich zusammenfällt"
      ],
      "urls": [
        "https://www.cicero.de/kultur/sanktionen-soziales-rostock",
        "https://www.cicero.de/kultur/markus-soder-bei-caren-miosga-reformpaket",
        "https://www.cicero.de/wirtschaft/stiftung-familienunternehmen-dgb-reformdebatte",
        "https://www.cicero.de/wirtschaft/burgergeld-portugal-schmarotzer-wie-eine-medienerzahlung-in-sich-zusammenfallt"
      ],
      "dominant_emotion": "neutral",
      "top_emotions": []
    },
    "achgut": {
      "source_id": "achgut",
      "source": "Achse des Guten",
      "bias": "far-right",
      "article_count": 1,
      "sample_titles": [
        "Wer hat’s gesagt? Fachkräftemangel beginnt „schon auf Kabinettsebene“"
      ],
      "urls": [
        "https://www.achgut.com/artikel/wer_hats_gesagt_deutscher_Fachkraeftemangel_beginnt_schon_auf_Kabinettsebene"
      ],
      "dominant_emotion": "curiosity",
      "top_emotions": [
        {
          "emotion": "curiosity",
          "count": 1
        }
      ]
    }
  },
  "bias_distribution": {
    "right-conservative": 102,
    "left-liberal": 109,
    "populist-mixed": 28,
    "neutral": 93,
    "far-right": 18,
    "economic-liberal": 38,
    "conservative-liberal": 57,
    "left": 13
  },
  "shared_perspectives": "# Inhaltliche Gemeinsamkeiten im deutschen Mediendiskurs zur Zukunft der Arbeit\n\nUnabhängig von politischer Ausrichtung besteht im deutschen Mediendiskurs Konsens darüber, dass die Arbeitszeitregulation ein zentrales Konfliktfeld ist — während konservative und wirtschaftsliberale Medien Flexibilisierung fordern, argumentieren progressive Medien für Modernisierung, doch alle behandeln dies als legitimes Gestaltungsfeld staatlicher Arbeitsmarktpolitik und nicht als rein private Angelegenheit. Zweiter Konsens betrifft die faktische Realität eines absehbaren oder bereits eingetretenen Fachkräftemangels und strukturellen Beschäftigungsverfalls in der Industrie — selbst populistische und wirtschaftsliberale Medien, die sonst gegensätzliche Lösungsansätze propagieren, akzeptieren diese Diagnose als empirische Grundlage, unterscheiden sich jedoch in der Ursachenzuschreibung (Zuwanderung vs. Digitalisierung vs. Unterinvestition). Die dritte Gemeinsamkeit liegt in der Akzeptanz, dass Bürgergeld und soziale Grundsicherung reformbedürftig sind — selbst linke Medien sprechen von einem „harten Kampf\" um die neue Grundsicherung, während konservative Medien Kürzungen fordern, was zeigt, dass der Legitimationsdruck zur Umgestaltung der Transfersysteme über alle Lager hinweg wirkt.",
  "controversial_points": "# Strukturelle Konfliktlinien im deutschen Mediendiskurs zur Zukunft der Arbeit\n\nDer zentrale Konflikt verläuft zwischen zwei inkompatiblen Diagnosen der Arbeitsmarktsituation: Während konservative und populistische Medien Bürgergeld-Empfänger als strukturelles Angebot-Problem darstellen, das durch Leistungskürzungen und \"Fördern und Fordern\" gelöst werden soll, identifizieren linke und gewerkschaftliche Medien systematische Unterversorgung bei Rechten, Sicherung und Löhnen als eigentliches Problem – diese Positionen schließen sich gegenseitig aus, weil sie auf völlig unterschiedlichen Annahmen über Arbeitsmarktdynamiken basieren.\n\nEin zweiter struktureller Konflikt trennt ökonomisch-liberal argumentierende Medien, die Flexibilisierung, individuelle Wahlrechte beim Kündigungsschutz und Deregulierung als Wachstumspfade propagieren, von einem sozialdemokratisch-gewerkschaftlichen Diskurs, der diese Maßnahmen als Erosion von Schutzstandards kritisiert – hier treffen gegensätzliche Verständnisse davon aufeinander, ob mehr Unsicherheit oder mehr Sicherheit Beschäftigung schafft.\n\nDie dritte Konfliktlinie betrifft die Frage von Mitbestimmung und Umverteilung: Rechts-konservative und wirtschaftsliberale Medien rahmen Gewerkschaftsforderungen zu Betriebsrenten, Lohngleichheit und Steuerprogression als \"Neid\" oder \"Bürokratie\", während linke Medien diese als notwendige Korrektive von Marktmechanismen darstellen – es geht um die grundsätzliche Legitimität kollektiver Interessenvertretung gegen Kapitalinteressen im deutschen Wirtschaftsmodell.",
  "cached_at": "2026-06-21T08:54:41.131020"
}